README.md
setup.py
graphkke/__init__.py
graphkke/graphkke.py
graphkke/kernels.py
graphkke/utils.py
graphkke.egg-info/PKG-INFO
graphkke.egg-info/SOURCES.txt
graphkke.egg-info/dependency_links.txt
graphkke.egg-info/requires.txt
graphkke.egg-info/top_level.txt
graphkke/graph/GraphLib_c.i